[{"ward":"Agrowisata","district":"Rumbai","regency":"Pekanbaru","province":"Riau","postcode":28264},{"ward":"Air Hitam","district":"Payung Sekaki","regency":"Pekanbaru","province":"Riau","postcode":28292},{"ward":"Airdingin","district":"Bukit Raya","regency":"Pekanbaru","province":"Riau","postcode":28284},{"ward":"Airputih","district":"Tampan","regency":"Pekanbaru","province":"Riau","postcode":28296},{"ward":"Bambukuning","district":"Tenayan Raya","regency":"Pekanbaru","province":"Riau","postcode":28281},{"ward":"Bandarraya","district":"Payung Sekaki","regency":"Pekanbaru","province":"Riau","postcode":28292},{"ward":"Bencahlesung (Sail)","district":"Tenayan Raya","regency":"Pekanbaru","province":"Riau","postcode":28285},{"ward":"Binawidya","district":"Tampan","regency":"Pekanbaru","province":"Riau","postcode":28295},{"ward":"Cinta Raja","district":"Sail","regency":"Pekanbaru","province":"Riau","postcode":28131}]